Mealy_NonOverlap_101111_Sequence_Detector/mealy_non_over_101111.v
//Design

module mealy_non_overlapping_101111 (input clk, rst, x, output z);
  parameter s0 = 3'b000;
  parameter s1 = 3'b001;
  parameter s2 = 3'b010;
  parameter s3 = 3'b011;
  parameter s4 = 3'b100; 
  parameter s5 = 3'b101;
  
  reg [3:0] state, next_state;
  
  always @(posedge clk or posedge rst) begin
    if(rst) begin 
      state <= s0;
    end
    else state <= next_state;
  end
  
  always @(state or x) begin
    case(state)
      s0: begin
           if(x == 0) next_state = s0;
           else       next_state = s1;
         end
      s1: begin
           if(x == 0) next_state = s2;
           else       next_state = s1;
         end
      s2: begin
           if(x == 0) next_state = s0;
           else       next_state = s3;
         end
      s3: begin
           if(x == 0) next_state = s2;
           else       next_state = s4;
         end
      s4: begin
           if(x == 0) next_state = s2;
           else       next_state = s5; 
         end
      s5: begin
           if(x == 0) next_state = s0;
           else       next_state = s0;
         end
      default: next_state = s0;
    endcase
  end
  assign z = (state == s5)? 1:0;
endmodule

Mealy_NonOverlap_101111_Sequence_Detector/mealy_non_over_101111_testbench.v
//Testbench

module TB;
  reg clk, rst, x;
  wire z;
  
  mealy_non_overlapping_101111 dut (clk, rst, x, z);
  initial clk = 0;   
  always #2 clk = ~clk;
    
  initial begin
    $monitor("%t: x = %b, z = %b",  $time, x, z);
    x = 0;
    #1 rst = 1;
    #2 rst = 0;
    
    #3 x = 1;
    #4 x = 1;
    #4 x = 0;
    #4 x = 1;
    #4 x = 1;
    #4 x = 1;
    #4 x = 1;
    #4 x = 0;
    #4 x = 0;
    #4 x = 1;
    #4 x = 0;
    #4 x = 1;
    #4 x = 1;
    #4 x = 1;
    #4 x = 1;
    #4 x = 0;
    #4 x = 1;
    #4 x = 1;
    #4 x = 1;
    #4 x = 1;
    #10;
    $finish;
  end
  
  initial begin
    $dumpfile("dump.vcd");
    $dumpvars(0);
  end
endmodule

Mealy_NonOverlap_101111_Sequence_Detector/dump.vcd
$date
	Thu Jun 22 20:27:47 2023
$end
$version
	Icarus Verilog
$end
$timescale
	1s
$end
$scope module TB $end
$var wire 1 ! z $end
$var reg 1 " clk $end
$var reg 1 # rst $end
$var reg 1 $ x $end
$scope module dut $end
$var wire 1 " clk $end
$var wire 1 # rst $end
$var wire 1 $ x $end
$var wire 1 ! z $end
$var reg 4 % next_state [3:0] $end
$var reg 4 & state [3:0] $end
$upscope $end
$upscope $end
$enddefinitions $end
#0
$dumpvars
bx &
b0 %
0$
x#
0"
x!
$end
#1
0!
b0 &
1#
#2
1"
#3
0#
#4
0"
#6
b1 &
b1 %
1"
1$
#8
0"
#10
1"
#12
0"
#14
b10 &
b0 %
1"
0$
#16
0"
#18
b11 &
b100 %
1"
1$
#20
0"
#22
b101 %
b100 &
1"
#24
0"
#26
1!
b0 %
b101 &
1"
#28
0"
#30
0!
b1 %
b0 &
1"
#32
0"
#34
b0 %
1"
0$
#36
0"
#38
1"
#40
0"
#42
b1 &
b1 %
1"
1$
#44
0"
#46
b10 &
b0 %
1"
0$
#48
0"
#50
b11 &
b100 %
1"
1$
#52
0"
#54
b101 %
b100 &
1"
#56
0"
#58
1!
b0 %
b101 &
1"
#60
0"
#62
0!
b1 %
b0 &
1"
#64
0"
#66
b0 %
1"
0$
#68
0"
#70
b1 &
b1 %
1"
1$
