Moore_Overlap_1111001_Sequence_Detector/moore_over_1111001.v
//Design

module moore_overlapping_1111001 (input clk, rst, x, output z);
  parameter s0 = 3'b000;
  parameter s1 = 3'b001;
  parameter s2 = 3'b010;
  parameter s3 = 3'b011;
  parameter s4 = 3'b100; 
  parameter s5 = 3'b101;
  parameter s6 = 3'b110; 
  parameter s7 = 3'b111;
  
  reg [2:0] state, next_state;
  
  always @(posedge clk or posedge rst) begin
    if(rst) begin 
      state <= s0;
    end
    else state <= next_state;
  end
  
  always @(state or x) begin
    case(state)
      s0: begin
           if(x == 0) next_state = s0;
           else       next_state = s1;
         end
      s1: begin
           if(x == 0) next_state = s0;
           else       next_state = s2;
         end
      s2: begin
           if(x == 0) next_state = s0;
           else       next_state = s3;
         end
      s3: begin
           if(x == 0) next_state = s0;
           else       next_state = s4;
         end
      s4: begin
           if(x == 0) next_state = s5;
           else       next_state = s4; 
         end
      s5: begin
           if(x == 0) next_state = s6;
           else       next_state = s1;
         end
      s6: begin
           if(x == 0) next_state = s0;
           else       next_state = s7; 
         end
      s7: begin
           if(x == 0) next_state = s0;
           else       next_state = s2;
         end
      default: next_state = s0;
    endcase
  end
  assign z = (state == s7)? 1:0;
endmodule

Moore_Overlap_1111001_Sequence_Detector/moore_over_1111001_testbench.v
//Testbench

module TB;
  reg clk, rst, x;
  wire z;
  
  moore_overlapping_1111001 dut (clk, rst, x, z);
  initial clk = 0;   
  always #2 clk = ~clk;
    
  initial begin
    $monitor("%t: x = %b, z = %b",  $time, x, z);
    x = 0;
    #1 rst = 1;
    #2 rst = 0;
    
    #3 x = 1;
    #4 x = 1;
    #4 x = 1;
    #4 x = 1;
    #4 x = 0;
    #4 x = 0;
    #4 x = 1;
    #4 x = 0;
    #4 x = 1;
    #4 x = 1;
    #4 x = 1;
    #4 x = 1;
    #4 x = 0;
    #4 x = 0;
    #4 x = 1;
    #4 x = 0;
    #4 x = 1;
    #4 x = 1;
    #4 x = 1;
    #10;
    $finish;
  end
  
  initial begin
    $dumpfile("dump.vcd");
    $dumpvars(0);
  end
endmodule

Moore_Overlap_1111001_Sequence_Detector/dump.vcd
$date
	Fri Jun 23 10:19:27 2023
$end
$version
	Icarus Verilog
$end
$timescale
	1s
$end
$scope module TB $end
$var wire 1 ! z $end
$var reg 1 " clk $end
$var reg 1 # rst $end
$var reg 1 $ x $end
$scope module dut $end
$var wire 1 " clk $end
$var wire 1 # rst $end
$var wire 1 $ x $end
$var wire 1 ! z $end
$var reg 3 % next_state [2:0] $end
$var reg 3 & state [2:0] $end
$upscope $end
$upscope $end
$enddefinitions $end
#0
$dumpvars
bx &
b0 %
0$
x#
0"
x!
$end
#1
0!
b0 &
1#
#2
1"
#3
0#
#4
0"
#6
b1 &
b10 %
1"
1$
#8
0"
#10
b11 %
b10 &
1"
#12
0"
#14
b100 %
b11 &
1"
#16
0"
#18
b100 &
1"
#20
0"
#22
b101 &
b110 %
1"
0$
#24
0"
#26
b0 %
b110 &
1"
#28
0"
#30
1!
b111 &
b10 %
1"
1$
#32
0"
#34
0!
b0 &
b0 %
1"
0$
#36
0"
#38
b1 &
b10 %
1"
1$
#40
0"
#42
b11 %
b10 &
1"
#44
0"
#46
b100 %
b11 &
1"
#48
0"
#50
b100 &
1"
#52
0"
#54
b101 &
b110 %
1"
0$
#56
0"
#58
b0 %
b110 &
1"
#60
0"
#62
1!
b111 &
b10 %
1"
1$
#64
0"
#66
0!
b0 &
b0 %
1"
0$
#68
0"
#70
b1 &
b10 %
1"
1$
#72
0"
#74
b11 %
b10 &
1"
#76
0"
#78
b100 %
b11 &
1"
#80
0"
#82
b100 &
1"
